{
  "_fv": 47,
  "_type": "gui",
  "definition": {
    "type": 0,
    "width": 176,
    "height": 166,
    "inventoryOffsetX": 0,
    "inventoryOffsetY": 0,
    "renderBgLayer": true,
    "doesPauseGame": false,
    "components": [
      {
        "type": "entitymodel",
        "data": {
          "entityModel": {
            "name": "TrexMedalGUIReturn"
          },
          "scale": 10,
          "rotationX": 45,
          "followMouseMovement": true,
          "x": 240,
          "y": 80
        }
      },
      {
        "type": "label",
        "data": {
          "name": "label_health",
          "text": {
            "fixedValue": "Health:"
          },
          "color": {
            "value": -12829636,
            "falpha": 0.0
          },
          "x": 132,
          "y": 53
        }
      },
      {
        "type": "label",
        "data": {
          "name": "label_attack",
          "text": {
            "fixedValue": "Attack:"
          },
          "color": {
            "value": -12829636,
            "falpha": 0.0
          },
          "x": 132,
          "y": 62
        }
      },
      {
        "type": "label",
        "data": {
          "name": "label_defense",
          "text": {
            "fixedValue": "Defense:"
          },
          "color": {
            "value": -12829636,
            "falpha": 0.0
          },
          "x": 132,
          "y": 71
        }
      },
      {
        "type": "label",
        "data": {
          "name": "label_accuracy",
          "text": {
            "fixedValue": "Accuracy:"
          },
          "color": {
            "value": -12829636,
            "falpha": 0.0
          },
          "x": 132,
          "y": 80
        }
      },
      {
        "type": "label",
        "data": {
          "name": "label_speed",
          "text": {
            "fixedValue": "Speed:"
          },
          "color": {
            "value": -12829636,
            "falpha": 0.0
          },
          "x": 132,
          "y": 89
        }
      },
      {
        "type": "label",
        "data": {
          "name": "label_support_attack",
          "text": {
            "fixedValue": "Support Attack:"
          },
          "color": {
            "value": -12829636,
            "falpha": 0.0
          },
          "x": 132,
          "y": 116
        }
      },
      {
        "type": "label",
        "data": {
          "name": "label_support_defense",
          "text": {
            "fixedValue": "Support Defense:"
          },
          "color": {
            "value": -12829636,
            "falpha": 0.0
          },
          "x": 132,
          "y": 125
        }
      },
      {
        "type": "label",
        "data": {
          "name": "label_support_accuracy",
          "text": {
            "fixedValue": "Support Accuracy:"
          },
          "color": {
            "value": -12829636,
            "falpha": 0.0
          },
          "x": 132,
          "y": 134
        }
      },
      {
        "type": "label",
        "data": {
          "name": "label_supportspeed",
          "text": {
            "fixedValue": "Support Speed:"
          },
          "color": {
            "value": -12829636,
            "falpha": 0.0
          },
          "x": 132,
          "y": 143
        }
      },
      {
        "type": "label",
        "data": {
          "name": "label_rank",
          "text": {
            "fixedValue": "Rank:"
          },
          "color": {
            "value": -12829636,
            "falpha": 0.0
          },
          "x": 132,
          "y": 44
        }
      },
      {
        "type": "label",
        "data": {
          "name": "label_proc_rank_return",
          "text": {
            "fixedValue": "",
            "name": "RankReturn"
          },
          "color": {
            "value": -12829636,
            "falpha": 0.0
          },
          "x": 177,
          "y": 44
        }
      }
    ],
    "gridSettings": {
      "sx": 18,
      "sy": 18,
      "ox": 11,
      "oy": 15,
      "snapOnGrid": true
    }
  }
}